aw11/__init__.py
aw11/clean.py
aw11/version.py
aw11-0.1.0.dist-info/LICENSE
aw11-0.1.0.dist-info/METADATA
aw11-0.1.0.dist-info/WHEEL
aw11-0.1.0.dist-info/entry_points.txt
aw11-0.1.0.dist-info/top_level.txt
aw11-0.1.0.dist-info/RECORD
