Metadata-Version: 2.1
Name: aw11
Version: 0.1.0
Summary: Code and config formatting and linting.
Home-page: https://github.com/esoma/aw11
Author: Erik Soma
Author-email: stillusingirc@gmail.com
License: UNKNOWN
Platform: UNKNOWN
Classifier: Development Status :: 4 - Beta
Classifier: Intended Audience :: Developers
Classifier: License :: OSI Approved :: MIT License
Classifier: Operating System :: OS Independent
Classifier: Programming Language :: Python :: 3
Requires-Python: >=3.6
